Metadata-Version: 2.1
Name: soda-core-fabric
Version: 3.5.6
License-File: LICENSE
Requires-Dist: soda-core-sqlserver==3.5.6
